Topsis_Samarjeet_102103562/topsis.py
Topsis_Samarjeet_102103562-1.0.0.dist-info/METADATA
Topsis_Samarjeet_102103562-1.0.0.dist-info/WHEEL
Topsis_Samarjeet_102103562-1.0.0.dist-info/entry_points.txt
Topsis_Samarjeet_102103562-1.0.0.dist-info/license.txt
Topsis_Samarjeet_102103562-1.0.0.dist-info/top_level.txt
Topsis_Samarjeet_102103562-1.0.0.dist-info/RECORD
